Workbook

Sheet Read me
A1: Architecture principle register
A2: Five sheets. The register holds the set with its implications and exception routes; the candidates sheet is where derivation happens; citations and exceptions are what prove the set is real; the health sheet tells you which principles have stopped working.
A4: The sheets
A5: Candidates - the desk-pass output. Source, draft statement, and the five tests. A candidate that fails the first test is deleted, not reworded.
A6: Principles - the adopted set. Five to seven rows, each with the seven parts, an owner, and a review date.
A7: Citations - every decision record that cited a principle. This sheet is the evidence that the set is being used.
A8: Exceptions - registered deviations with expiry. A principle whose violations are recorded is a principle that is working.
A9: Health - computed per principle: citations, exceptions, and the verdict.
A11: The falsifiability test
A12: Name a real decision from the last year where this principle would have forced the less comfortable option. If you cannot, delete it - not because the sentiment is wrong, but because the sentiment is already shared, and shared sentiments do not need governance.
A13: A second test: does the opposite sound insane, or merely different? 'We prefer secure systems' fails; the opposite is absurd. 'We buy with configuration over building, even where building would fit better' passes, because plenty of good organizations do the opposite deliberately.
A15: Two decay patterns to watch at the annual review
... A22: Companion article: mehdibamou.com/publications/architecture-principles - free to use and adapt

Sheet Lists
A1: Strategy | B1: Candidate | C1: Pass | D1: Applying | E1: Open
A2: Decision log | B2: Adopted | C2: Fail | D2: Exception | E2: Closed
A3: Incidents | B3: Rejected | E3: Extended
A4: Constraints | B4: Retired | E4: Promoted to standard
A5: What we are bad at

Sheet Candidates
A1: # | B1: Source | C1: Evidence (the specific thing) | D1: Draft statement (X over Y) | E1: Test 1 - decision it would have reversed | F1: Test 2 - opposite merely different? | G1: Test 3 - who loses | H1: Test 4 - cost accepted | I1: Test 5 - recallable | J1: Verdict
A2: 1 | B2: Decision log | C2: Three separate arguments about copying data into a reporting store, resolved differently each time | D2: One system of record per object, even when a second copy would ship faster | E2: The Q2 reporting cache, approved in March, which caused two of last year's data incidents | F2: Pass | G2: The delivery team that wanted the campaign live three weeks earlier | H2: Some projects wait for the owning system to expose what they need | I2: Pass | J2: Adopted
A3: 2 | B3: Strategy | C3: Board commitment to grow by acquisition, two units a year | D3: Absorbability over elegance in shared capabilities | E3: The identity redesign that assumed one directory forever | F3: Pass | G3: Platform teams, who carry an extra seam | H3: Shared services carry configuration they would rather not have | I3: Pass | J3: Adopted
A4: 3 | B4: Incidents | C4: Four of last year's six incidents traced to changes that could not be reversed quickly | D4: Reversibility over efficiency | E4: The batch migration cutover with no rollback path, approved last September | F4: Pass | G4: Anyone shipping the fastest version of a change | H4: Some designs cost 15 to 20 per cent more to build | I4: Pass | J4: Adopted
A5: 4 | B5: What we are bad at | C5: Run cost never estimated at design time; two platforms now cost more to operate than to have built | D5: Run cost named at design time over speed to first demo | E5: The analytics platform approved in January with no operating estimate | F5: Pass | G5: Project teams under a demo deadline | H5: A week of design time added to most builds | I5: Pass | J5: Adopted
A6: 5 | B6: Constraints | C6: Regulator requires reconstruction of any figure within ten working days | D6: Traceable over convenient | E6: The direct-write integration built in April, which has no audit record | F6: Pass | G6: Integration teams, on every small internal flow | H6: Logging is not optional even where it feels disproportionate | I6: Pass | J6: Adopted
A7: 6 | B7: Strategy | C7: Statement that technology should be fit for purpose | D7: Fit-for-purpose technology | E7: Nothing - no decision would have gone differently | F7: Fail | G7: Nobody | H7: None nameable | I7: Pass | J7: Rejected
A8: 7 | B8: Decision log | C8: Recurring debate about build versus buy in the domain teams | D8: Configuration over build, even where building would fit better | E8: The workflow tool built in-house in Q3 rather than configured | F8: Pass | G8: Engineering teams who prefer to build | H8: We accept a worse fit in exchange for a supported product | I8: Pass | J8: Adopted
A9: 8 | B9: Incidents | C9: Data is an asset - inherited from the previous framework set | D9: Data is an asset | E9: None that can be named | F9: Fail | G9: Nobody, ever | H9: None | I9: Pass | J9: Rejected

Sheet Principles
A1: ID | B1: Statement (X over Y) | C1: Rationale - for this organization | D1: Implications (the cost we accept) | E1: Test (five minutes, by an architect) | F1: Exception route | G1: Default expiry | H1: Owner | I1: Adopted | J1: Next review | K1: Status
A2: P-01 | B2: One system of record per object, even when a second copy would ship faster | C2: Three of last year's four data incidents came from two systems believing they owned the same object | D2: Some projects wait for the owning system to expose what they need | E2: Does anything here create or change an object another system masters? | F2: Read-only cache with a named expiry, registered | G2: 12 months | H2: Data architect | I2: 45852 | J2: 46217 | K2: Adopted
A3: P-02 | B3: Absorbability over elegance in shared capabilities | C3: The board has committed to two acquisitions a year; the last integration took five quarters | D3: Shared services carry configuration seams they would rather not have | E3: Could an acquired unit be onboarded to this within two quarters, without a redesign? | F3: Registered deviation with a named sponsor | G3: 12 months | H3: Domain architect | I3: 45852 | J3: 46217 | K3: Adopted
A4: P-03 | B4: Standard processes over local optimization | C4: The last two rollouts each cost a quarter to reconcile market variants nobody had asked for in writing | D4: Some markets run a process measurably worse for them; we fund the difference centrally where it bites hardest | E4: Does this introduce a variant only one market uses, and is it on the fit-gap list? | F4: Registered deviation, reviewed at twelve months | G4: 12 months | H4: Programme architect | I4: 45852 | J4: 46217 | K4: Adopted
A5: P-04 | B5: Reversibility over efficiency | C5: Four of last year's six incidents traced to changes that could not be reversed quickly | D5: Some designs cost 15 to 20 per cent more to build | E5: Can this be undone within one working day, and has that been tested? | F5: Board approval for a one-way door, with the reason recorded | G5: 6 months | H5: Chief architect | I5: 45852 | J5: 46217 | K5: Adopted
A6: P-05 | B6: Run cost named at design time over speed to first demo | C6: Two platforms now cost more to operate than they cost to build; neither had an operating estimate | D6: A week of design time added to most builds | E6: Is there an annual run cost on the design page, with a name against it? | F6: None - the estimate can be rough, but it cannot be absent | G6: - | H6: Chief architect | I6: 45852 | J6: 46217 | K6: Adopted
A7: P-06 | B7: Configuration over build, even where building would fit better | C7: The in-house workflow tool built in Q3 now has one maintainer and no roadmap | D7: We accept a worse fit in exchange for a supported product | E7: Has the standard product been demonstrated against this requirement with real data? | F7: Registered, with the gap documented and a review at twelve months | G7: 12 months | H7: Domain architect | I7: 45964 | J7: 46329 | K7: Adopted
A8: P-07 | B8: Traceable over convenient | C8: An audit finding two years ago cost more than that year's entire integration budget | D8: Every interface logs, including small internal flows | E8: Can any figure this touches be reconstructed within ten working days? | F8: Signed off by the compliance lead, not by architecture | G8: 6 months | H8: Compliance lead | I8: 45964 | J8: 46329 | K8: Adopted
A18: Five to seven. Fewer misses the recurring arguments; more cannot be recalled in the corridor, which is where they matter.
A19: Note that P-05 has no exception route on purpose. The estimate can be rough; it cannot be absent. Say so explicitly, or someone will assume there is a route and be surprised.

Sheet Citations
A1: Date | B1: Decision ref | C1: Principle | D1: Applying or exception | E1: How it was used | F1: Outcome
A2: 45875 | B2: ADR-041 | C2: P-01 | D2: Applying | E2: Reporting team asked for a writable copy of customer; refused, read-only cache registered instead | F2: Cache with a six-month expiry, since retired
A3: 45902 | B3: ADR-046 | C3: P-04 | D3: Applying | E3: Migration cutover redesigned to keep the old path warm for two weeks | F3: Rollback used once, in week one
A4: 45930 | B4: ADR-052 | C4: P-03 | D4: Exception | E4: Market with a statutory posting requirement | F4: Registered, expiry 2026-07-31, funded centrally
A5: 45951 | B5: ADR-058 | C5: P-02 | D5: Applying | E5: Identity design changed to allow a second directory during onboarding | F5: Added four weeks; used six months later
A6: 45979 | B6: ADR-063 | C6: P-05 | D6: Applying | E6: Analytics platform sent back for an operating estimate before approval | F6: Estimate came back at three times the assumption; scope reduced
A7: 46035 | B7: ADR-071 | C7: P-01 | D7: Applying | E7: Second write path into supplier refused; event contract added instead | F7: Interface INT-001
A8: 46057 | B8: ADR-074 | C8: P-06 | D8: Exception | E8: Bespoke picking sequence for one market | F8: Fit-gap list, review in twelve months
A9: 46077 | B9: ADR-077 | C9: P-07 | D9: Applying | E9: Small internal flow required logging that the team considered disproportionate | F9: Logged; used in an audit six weeks later
A10: 46098 | B10: ADR-081 | C10: P-03 | D10: Applying | E10: Delivery team invoked it against an architecture request for a bespoke variant | F10: Request withdrawn - the best day of the year
A11: 46120 | B11: ADR-085 | C11: P-04 | D11: Exception | E11: One-way data migration with no practical rollback | F11: Board approved, reason recorded, monitoring added
A12: 46154 | B12: ADR-090 | C12: P-01 | D12: Applying | E12: Campaign tool asked for a local customer store | F12: Read via API; campaign shipped two weeks later than hoped
A13: 46175 | B13: ADR-094 | C13: P-06 | D13: Applying | E13: Workflow requirement met by configuring the standard product | F13: Four weeks saved against the build estimate

Sheet Exceptions
A1: Ref | B1: Raised | C1: Principle | D1: Requested by | E1: What is being deviated from | F1: Reason | G1: Approved by | H1: Expiry | I1: Days to expiry | J1: Status
A2: EXC-01 | B2: 45930 | C2: P-03 | D2: Market C | E2: Standard goods movement posting | F2: Statutory valuation basis differs | G2: Programme board | H2: 46234 | I2: =IF(H2="","",H2-DATE(2026,6,30)) | J2: Open
A3: EXC-02 | B3: 45944 | C3: P-01 | D3: Reporting | E3: Read-only copy of customer refreshed nightly | F3: Reporting latency during month-end close | G3: Data architect | H3: 46126 | I3: =IF(H3="","",H3-DATE(2026,6,30)) | J3: Closed
A4: EXC-03 | B4: 46057 | C4: P-06 | D4: Market F | E4: Bespoke picking sequence rather than configuration | F4: Warehouse layout predates the standard | G4: Domain architect | H4: 46422 | I4: =IF(H4="","",H4-DATE(2026,6,30)) | J4: Open
A5: EXC-04 | B5: 46120 | C5: P-04 | D5: Data platform | E5: One-way migration with no rollback | F5: Source system decommissioned same weekend | G5: Board | H5: 46142 | I5: =IF(H5="","",H5-DATE(2026,6,30)) | J5: Closed
A6: EXC-05 | B6: 46162 | C6: P-07 | D6: Internal tools | E6: Logging omitted on an internal status flow | F6: Volume made per-event logging disproportionate | G6: Compliance lead | H6: 46346 | I6: =IF(H6="","",H6-DATE(2026,6,30)) | J6: Open
I7: =IF(H7="","",H7-DATE(2026,6,30))
I8: =IF(H8="","",H8-DATE(2026,6,30))
I9: =IF(H9="","",H9-DATE(2026,6,30))
I10: =IF(H10="","",H10-DATE(2026,6,30))
I11: =IF(H11="","",H11-DATE(2026,6,30))
I12: =IF(H12="","",H12-DATE(2026,6,30))
I13: =IF(H13="","",H13-DATE(2026,6,30))
I14: =IF(H14="","",H14-DATE(2026,6,30))
I15: =IF(H15="","",H15-DATE(2026,6,30))
I16: =IF(H16="","",H16-DATE(2026,6,30))
I17: =IF(H17="","",H17-DATE(2026,6,30))
I18: =IF(H18="","",H18-DATE(2026,6,30))
... I121: =IF(H121="","",H121-DATE(2026,6,30))
A123: Change the date in column I to your own as-at date, or point it at a Settings cell.

Sheet Health
A1: ID | B1: Statement | C1: Citations | D1: Exceptions | E1: Open exceptions | F1: Verdict | G1: What to do
A2: =IF(Principles!A2="","",Principles!A2) | B2: =IF(Principles!A2="","",Principles!B2) | C2: =IF(A2="","",COUNTIF(Citations!$C$2:$C$201,A2)) | D2: =IF(A2="","",COUNTIF(Exceptions!$C$2:$C$121,A2)) | E2: =IF(A2="","",COUNTIFS(Exceptions!$C$2:$C$121,A2,Exceptions!$J$2:$J$121,"Open")) | F2: =IF(A2="","",IF(AND(C2=0,D2=0),"Decorative - retire",IF(AND(C2>0,D2=0),"Held without exception",IF(E2>2,"Contested - reword or accept","Working")))) | G2: =IF(A2="","",IF(AND(C2=0,D2=0),"Nobody cited it and nobody deviated from it. Either the behaviour is now normal, or it never bit. Retire it at this review",IF(AND(C2>0,D2=0),"Check it is not simply restating what people would do anyway",IF(E2>2,"Three or more open exceptions means the principle is describing an intention rather than a rule. Reword it or accept the reality","Leave it alone"))))
A3: =IF(Principles!A3="","",Principles!A3) | B3: =IF(Principles!A3="","",Principles!B3) | C3: =IF(A3="","",COUNTIF(Citations!$C$2:$C$201,A3)) | D3: =IF(A3="","",COUNTIF(Exceptions!$C$2:$C$121,A3)) | E3: =IF(A3="","",COUNTIFS(Exceptions!$C$2:$C$121,A3,Exceptions!$J$2:$J$121,"Open")) | F3: =IF(A3="","",IF(AND(C3=0,D3=0),"Decorative - retire",IF(AND(C3>0,D3=0),"Held without exception",IF(E3>2,"Contested - reword or accept","Working")))) | G3: =IF(A3="","",IF(AND(C3=0,D3=0),"Nobody cited it and nobody deviated from it. Either the behaviour is now normal, or it never bit. Retire it at this review",IF(AND(C3>0,D3=0),"Check it is not simply restating what people would do anyway",IF(E3>2,"Three or more open exceptions means the principle is describing an intention rather than a rule. Reword it or accept the reality","Leave it alone"))))
A4: =IF(Principles!A4="","",Principles!A4) | B4: =IF(Principles!A4="","",Principles!B4) | C4: =IF(A4="","",COUNTIF(Citations!$C$2:$C$201,A4)) | D4: =IF(A4="","",COUNTIF(Exceptions!$C$2:$C$121,A4)) | E4: =IF(A4="","",COUNTIFS(Exceptions!$C$2:$C$121,A4,Exceptions!$J$2:$J$121,"Open")) | F4: =IF(A4="","",IF(AND(C4=0,D4=0),"Decorative - retire",IF(AND(C4>0,D4=0),"Held without exception",IF(E4>2,"Contested - reword or accept","Working")))) | G4: =IF(A4="","",IF(AND(C4=0,D4=0),"Nobody cited it and nobody deviated from it. Either the behaviour is now normal, or it never bit. Retire it at this review",IF(AND(C4>0,D4=0),"Check it is not simply restating what people would do anyway",IF(E4>2,"Three or more open exceptions means the principle is describing an intention rather than a rule. Reword it or accept the reality","Leave it alone"))))
A5: =IF(Principles!A5="","",Principles!A5) | B5: =IF(Principles!A5="","",Principles!B5) | C5: =IF(A5="","",COUNTIF(Citations!$C$2:$C$201,A5)) | D5: =IF(A5="","",COUNTIF(Exceptions!$C$2:$C$121,A5)) | E5: =IF(A5="","",COUNTIFS(Exceptions!$C$2:$C$121,A5,Exceptions!$J$2:$J$121,"Open")) | F5: =IF(A5="","",IF(AND(C5=0,D5=0),"Decorative - retire",IF(AND(C5>0,D5=0),"Held without exception",IF(E5>2,"Contested - reword or accept","Working")))) | G5: =IF(A5="","",IF(AND(C5=0,D5=0),"Nobody cited it and nobody deviated from it. Either the behaviour is now normal, or it never bit. Retire it at this review",IF(AND(C5>0,D5=0),"Check it is not simply restating what people would do anyway",IF(E5>2,"Three or more open exceptions means the principle is describing an intention rather than a rule. Reword it or accept the reality","Leave it alone"))))
A6: =IF(Principles!A6="","",Principles!A6) | B6: =IF(Principles!A6="","",Principles!B6) | C6: =IF(A6="","",COUNTIF(Citations!$C$2:$C$201,A6)) | D6: =IF(A6="","",COUNTIF(Exceptions!$C$2:$C$121,A6)) | E6: =IF(A6="","",COUNTIFS(Exceptions!$C$2:$C$121,A6,Exceptions!$J$2:$J$121,"Open")) | F6: =IF(A6="","",IF(AND(C6=0,D6=0),"Decorative - retire",IF(AND(C6>0,D6=0),"Held without exception",IF(E6>2,"Contested - reword or accept","Working")))) | G6: =IF(A6="","",IF(AND(C6=0,D6=0),"Nobody cited it and nobody deviated from it. Either the behaviour is now normal, or it never bit. Retire it at this review",IF(AND(C6>0,D6=0),"Check it is not simply restating what people would do anyway",IF(E6>2,"Three or more open exceptions means the principle is describing an intention rather than a rule. Reword it or accept the reality","Leave it alone"))))
A7: =IF(Principles!A7="","",Principles!A7) | B7: =IF(Principles!A7="","",Principles!B7) | C7: =IF(A7="","",COUNTIF(Citations!$C$2:$C$201,A7)) | D7: =IF(A7="","",COUNTIF(Exceptions!$C$2:$C$121,A7)) | E7: =IF(A7="","",COUNTIFS(Exceptions!$C$2:$C$121,A7,Exceptions!$J$2:$J$121,"Open")) | F7: =IF(A7="","",IF(AND(C7=0,D7=0),"Decorative - retire",IF(AND(C7>0,D7=0),"Held without exception",IF(E7>2,"Contested - reword or accept","Working")))) | G7: =IF(A7="","",IF(AND(C7=0,D7=0),"Nobody cited it and nobody deviated from it. Either the behaviour is now normal, or it never bit. Retire it at this review",IF(AND(C7>0,D7=0),"Check it is not simply restating what people would do anyway",IF(E7>2,"Three or more open exceptions means the principle is describing an intention rather than a rule. Reword it or accept the reality","Leave it alone"))))
A8: =IF(Principles!A8="","",Principles!A8) | B8: =IF(Principles!A8="","",Principles!B8) | C8: =IF(A8="","",COUNTIF(Citations!$C$2:$C$201,A8)) | D8: =IF(A8="","",COUNTIF(Exceptions!$C$2:$C$121,A8)) | E8: =IF(A8="","",COUNTIFS(Exceptions!$C$2:$C$121,A8,Exceptions!$J$2:$J$121,"Open")) | F8: =IF(A8="","",IF(AND(C8=0,D8=0),"Decorative - retire",IF(AND(C8>0,D8=0),"Held without exception",IF(E8>2,"Contested - reword or accept","Working")))) | G8: =IF(A8="","",IF(AND(C8=0,D8=0),"Nobody cited it and nobody deviated from it. Either the behaviour is now normal, or it never bit. Retire it at this review",IF(AND(C8>0,D8=0),"Check it is not simply restating what people would do anyway",IF(E8>2,"Three or more open exceptions means the principle is describing an intention rather than a rule. Reword it or accept the reality","Leave it alone"))))
A9: =IF(Principles!A9="","",Principles!A9) | B9: =IF(Principles!A9="","",Principles!B9) | C9: =IF(A9="","",COUNTIF(Citations!$C$2:$C$201,A9)) | D9: =IF(A9="","",COUNTIF(Exceptions!$C$2:$C$121,A9)) | E9: =IF(A9="","",COUNTIFS(Exceptions!$C$2:$C$121,A9,Exceptions!$J$2:$J$121,"Open")) | F9: =IF(A9="","",IF(AND(C9=0,D9=0),"Decorative - retire",IF(AND(C9>0,D9=0),"Held without exception",IF(E9>2,"Contested - reword or accept","Working")))) | G9: =IF(A9="","",IF(AND(C9=0,D9=0),"Nobody cited it and nobody deviated from it. Either the behaviour is now normal, or it never bit. Retire it at this review",IF(AND(C9>0,D9=0),"Check it is not simply restating what people would do anyway",IF(E9>2,"Three or more open exceptions means the principle is describing an intention rather than a rule. Reword it or accept the reality","Leave it alone"))))
A10: =IF(Principles!A10="","",Principles!A10) | B10: =IF(Principles!A10="","",Principles!B10) | C10: =IF(A10="","",COUNTIF(Citations!$C$2:$C$201,A10)) | D10: =IF(A10="","",COUNTIF(Exceptions!$C$2:$C$121,A10)) | E10: =IF(A10="","",COUNTIFS(Exceptions!$C$2:$C$121,A10,Exceptions!$J$2:$J$121,"Open")) | F10: =IF(A10="","",IF(AND(C10=0,D10=0),"Decorative - retire",IF(AND(C10>0,D10=0),"Held without exception",IF(E10>2,"Contested - reword or accept","Working")))) | G10: =IF(A10="","",IF(AND(C10=0,D10=0),"Nobody cited it and nobody deviated from it. Either the behaviour is now normal, or it never bit. Retire it at this review",IF(AND(C10>0,D10=0),"Check it is not simply restating what people would do anyway",IF(E10>2,"Three or more open exceptions means the principle is describing an intention rather than a rule. Reword it or accept the reality","Leave it alone"))))
A11: =IF(Principles!A11="","",Principles!A11) | B11: =IF(Principles!A11="","",Principles!B11) | C11: =IF(A11="","",COUNTIF(Citations!$C$2:$C$201,A11)) | D11: =IF(A11="","",COUNTIF(Exceptions!$C$2:$C$121,A11)) | E11: =IF(A11="","",COUNTIFS(Exceptions!$C$2:$C$121,A11,Exceptions!$J$2:$J$121,"Open")) | F11: =IF(A11="","",IF(AND(C11=0,D11=0),"Decorative - retire",IF(AND(C11>0,D11=0),"Held without exception",IF(E11>2,"Contested - reword or accept","Working")))) | G11: =IF(A11="","",IF(AND(C11=0,D11=0),"Nobody cited it and nobody deviated from it. Either the behaviour is now normal, or it never bit. Retire it at this review",IF(AND(C11>0,D11=0),"Check it is not simply restating what people would do anyway",IF(E11>2,"Three or more open exceptions means the principle is describing an intention rather than a rule. Reword it or accept the reality","Leave it alone"))))
A12: =IF(Principles!A12="","",Principles!A12) | B12: =IF(Principles!A12="","",Principles!B12) | C12: =IF(A12="","",COUNTIF(Citations!$C$2:$C$201,A12)) | D12: =IF(A12="","",COUNTIF(Exceptions!$C$2:$C$121,A12)) | E12: =IF(A12="","",COUNTIFS(Exceptions!$C$2:$C$121,A12,Exceptions!$J$2:$J$121,"Open")) | F12: =IF(A12="","",IF(AND(C12=0,D12=0),"Decorative - retire",IF(AND(C12>0,D12=0),"Held without exception",IF(E12>2,"Contested - reword or accept","Working")))) | G12: =IF(A12="","",IF(AND(C12=0,D12=0),"Nobody cited it and nobody deviated from it. Either the behaviour is now normal, or it never bit. Retire it at this review",IF(AND(C12>0,D12=0),"Check it is not simply restating what people would do anyway",IF(E12>2,"Three or more open exceptions means the principle is describing an intention rather than a rule. Reword it or accept the reality","Leave it alone"))))
A13: =IF(Principles!A13="","",Principles!A13) | B13: =IF(Principles!A13="","",Principles!B13) | C13: =IF(A13="","",COUNTIF(Citations!$C$2:$C$201,A13)) | D13: =IF(A13="","",COUNTIF(Exceptions!$C$2:$C$121,A13)) | E13: =IF(A13="","",COUNTIFS(Exceptions!$C$2:$C$121,A13,Exceptions!$J$2:$J$121,"Open")) | F13: =IF(A13="","",IF(AND(C13=0,D13=0),"Decorative - retire",IF(AND(C13>0,D13=0),"Held without exception",IF(E13>2,"Contested - reword or accept","Working")))) | G13: =IF(A13="","",IF(AND(C13=0,D13=0),"Nobody cited it and nobody deviated from it. Either the behaviour is now normal, or it never bit. Retire it at this review",IF(AND(C13>0,D13=0),"Check it is not simply restating what people would do anyway",IF(E13>2,"Three or more open exceptions means the principle is describing an intention rather than a rule. Reword it or accept the reality","Leave it alone"))))
... A15: =IF(Principles!A15="","",Principles!A15) | B15: =IF(Principles!A15="","",Principles!B15) | C15: =IF(A15="","",COUNTIF(Citations!$C$2:$C$201,A15)) | D15: =IF(A15="","",COUNTIF(Exceptions!$C$2:$C$121,A15)) | E15: =IF(A15="","",COUNTIFS(Exceptions!$C$2:$C$121,A15,Exceptions!$J$2:$J$121,"Open")) | F15: =IF(A15="","",IF(AND(C15=0,D15=0),"Decorative - retire",IF(AND(C15>0,D15=0),"Held without exception",IF(E15>2,"Contested - reword or accept","Working")))) | G15: =IF(A15="","",IF(AND(C15=0,D15=0),"Nobody cited it and nobody deviated from it. Either the behaviour is now normal, or it never bit. Retire it at this review",IF(AND(C15>0,D15=0),"Check it is not simply restating what people would do anyway",IF(E15>2,"Three or more open exceptions means the principle is describing an intention rather than a rule. Reword it or accept the reality","Leave it alone"))))
A18: A principle with zero citations and zero exceptions is not being used. That is a finding about the principle, not about the organization.
A19: Read the whole set aloud once a year and ask the falsifiability question again. Both decay patterns - inflation and drift into virtue - happen during rewrites by people trying to be helpful.
