Workbook

Sheet Read me
A1: Clean core - extension and integration register
A2: Four working sheets and a scorecard. The register is the mechanism: every request classified in public, every exception carrying an owner and an expiry, every quarter closing or extending or promoting what has expired.
A4: The sheets
A5: Settings - the as-at date, the default expiry, and the buy-out threshold. Change these before anything else.
A6: Extensions - the request log. Classification, place, funding, expiry, and the ages that make the register readable.
A7: Interfaces - the inventory. Contract type, direction, pattern, owner, and whether it runs on something released.
A8: Ownership - which system masters each significant object. One afternoon of argument, and it prevents more damage than any later governance.
A9: Buy-out candidates - anything appearing in the threshold number of markets or more. Computed, not curated.
A10: Scorecard - the four numbers, and a Trend sheet so the shape over a year is visible.
A12: How to run it
A13: 1. Every request gets a row in Extensions the day it arrives, before it is classified. A request that only enters the register once approved teaches people to route around the register.
A14: 2. Classify against the decision tree, by an architect, in public. Configuration and in-app first; side-by-side for substance; core modification only with a named approver and a date.
... A24: Companion article: mehdibamou.com/publications/clean-core-integration - free to use and adapt

Sheet Settings
A1: Setting | B1: Value | C1: Note
A2: Register as-at date | B2: 46203 | C2: Month end. Drives ages and the expiring view
A3: Default expiry (months) | B3: 12 | C3: For core modifications and heavy extensions
A4: Buy-out threshold (markets) | B4: 3 | C4: Same extension in this many markets or more becomes a central capability
A5: Warn before expiry (days) | B5: 60 | C5: How early an item shows as due
A6: Released-contract target | B6: 0.95 | C6: Set it where you intend to hold

Sheet Lists
A1: Configuration | B1: Statutory | C1: Requested | D1: API | E1: Inbound | F1: Released | G1: Market
A2: In-app extension | B2: Differentiating | C2: Classified | D2: Event | E2: Outbound | F2: Bridge - expiry set | G2: Central
A3: Side-by-side | B3: Historic preference | C3: Approved | D3: File | E3: Both | F3: Unreleased | G3: Group function
A4: Core modification | C4: Built | D4: Direct DB
A5: Fit-gap list | C5: Live | D5: Point-to-point
C6: Expiring
C7: Retired
C8: Bought out
C9: Rejected

Sheet Extensions
A1: Req ID | B1: Raised | C1: Market / function | D1: Requester | E1: Need (one line) | F1: Standard does today | G1: What breaks | H1: Bucket | I1: Place | J1: Status | K1: Owner | L1: Funded by | M1: Build est (days) | N1: Run cost / yr | O1: Expiry | P1: Days to expiry | Q1: Age (days) | R1: What would make this go away
A2: EXT-001 | B2: 45904 | C2: Market A | D2: H. Roth | E2: Extra approval on purchase orders over a threshold | F2: Release strategy exists but was never configured | G2: Nothing - the need is met once configured | H2: Historic preference | I2: Configuration | J2: Live | K2: H. Roth | L2: Market | M2: 2 | N2: 0 | P2: =IF(O2="","",O2-Settings!$B$2) | Q2: =IF(B2="",0,Settings!$B$2-B2) | R2: Already resolved - configuration
A3: EXT-002 | B3: 45919 | C3: Market B | D3: L. Nowak | E3: Statutory e-invoice layout | F3: Standard layout does not carry the required fields | G3: Invoices rejected by the tax authority | H3: Statutory | I3: In-app extension | J3: Live | K3: Localization lead | L3: Central | M3: 14 | N3: 4000 | O3: 46934 | P3: =IF(O3="","",O3-Settings!$B$2) | Q3: =IF(B3="",0,Settings!$B$2-B3) | R3: Vendor country version covers it from release 2028
A4: EXT-003 | B4: 45932 | C4: Market C | D4: S. Dubois | E4: Local supplier register check at goods receipt | F4: No equivalent check | G4: Manual reconciliation, two FTE days a week | H4: Historic preference | I4: Side-by-side | J4: Live | K4: Integration team | L4: Market | M4: 25 | N4: 12000 | O4: 46297 | P4: =IF(O4="","",O4-Settings!$B$2) | Q4: =IF(B4="",0,Settings!$B$2-B4) | R4: Group supplier master covers it once market C is migrated
A5: EXT-004 | B5: 45972 | C5: Market A | D5: H. Roth | E5: Custom pricing condition in the core | F5: Condition technique cannot express the rule | G5: Manual price overrides on 8 per cent of orders | H5: Differentiating | I5: Core modification | J5: Expiring | K5: Pricing architect | L5: Central | M5: 40 | N5: 30000 | O5: 46337 | P5: =IF(O5="","",O5-Settings!$B$2) | Q5: =IF(B5="",0,Settings!$B$2-B5) | R5: Side-by-side pricing service planned for Q4
A6: EXT-005 | B6: 45994 | C6: Market D | D6: P. Almeida | E6: Local supplier register check at goods receipt | F6: No equivalent check | G6: Manual reconciliation | H6: Historic preference | I6: Side-by-side | J6: Built | K6: Integration team | L6: Market | M6: 20 | N6: 9000 | O6: 46359 | P6: =IF(O6="","",O6-Settings!$B$2) | Q6: =IF(B6="",0,Settings!$B$2-B6) | R6: Same as EXT-003 - candidate for buy-out
A7: EXT-006 | B7: 46038 | C7: Market E | D7: N. Berg | E7: Local supplier register check at goods receipt | F7: No equivalent check | G7: Manual reconciliation | H7: Historic preference | I7: Side-by-side | J7: Approved | K7: Integration team | L7: Market | M7: 20 | N7: 9000 | O7: 46403 | P7: =IF(O7="","",O7-Settings!$B$2) | Q7: =IF(B7="",0,Settings!$B$2-B7) | R7: Third occurrence - buy-out threshold reached
A8: EXT-007 | B8: 46062 | C8: Group | D8: Finance | E8: Consolidated margin view across markets | F8: Reporting layer holds only posted figures | G8: Month-end close runs three days long | H8: Differentiating | I8: Side-by-side | J8: Built | K8: Data platform | L8: Group function | M8: 35 | N8: 18000 | P8: =IF(O8="","",O8-Settings!$B$2) | Q8: =IF(B8="",0,Settings!$B$2-B8) | R8: Permanent - owned capability, not an exception
A9: EXT-008 | B9: 46106 | C9: Market B | D9: L. Nowak | E9: Screen field added for local contract reference | F9: No field | G9: Reference kept in a spreadsheet | H9: Historic preference | I9: In-app extension | J9: Live | K9: L. Nowak | L9: Market | M9: 3 | N9: 500 | O9: 46471 | P9: =IF(O9="","",O9-Settings!$B$2) | Q9: =IF(B9="",0,Settings!$B$2-B9) | R9: Group contract object exposes the field from release 2027
A10: EXT-009 | B10: 46126 | C10: Market C | D10: S. Dubois | E10: Modified goods movement posting logic | F10: Standard posts at a different granularity | G10: Stock valuation differs from the local statutory basis | H10: Statutory | I10: Core modification | J10: Approved | K10: Logistics architect | L10: Central | M10: 30 | N10: 22000 | O10: 46234 | P10: =IF(O10="","",O10-Settings!$B$2) | Q10: =IF(B10="",0,Settings!$B$2-B10) | R10: Localization layer takes it over once the pattern is generalized
A11: EXT-010 | B11: 46148 | C11: Market F | D11: T. Ivanov | E11: Bespoke picking sequence | F11: Standard sequence differs | G11: Warehouse staff retraining | H11: Historic preference | I11: Fit-gap list | J11: Requested | K11: Ops architect | L11: Market | P11: =IF(O11="","",O11-Settings!$B$2) | Q11: =IF(B11="",0,Settings!$B$2-B11) | R11: Show the standard running with their data before deciding
A12: EXT-011 | B12: 45881 | C12: Market B | D12: L. Nowak | E12: Modified stock report layout in the core | F12: Standard report differs in grouping | G12: Local team reformats by hand each month | H12: Historic preference | I12: Core modification | J12: Retired | K12: Reporting lead | L12: Market | M12: 12 | N12: 6000 | O12: 46065 | P12: =IF(O12="","",O12-Settings!$B$2) | Q12: =IF(B12="",0,Settings!$B$2-B12) | R12: Retired at the Q1 review - switched off in test, nobody noticed for three weeks
A13: EXT-012 | B13: 45895 | C13: Market A | D13: H. Roth | E13: Modified credit check at order entry | F13: Standard check runs at a different point | G13: Orders released before the check | H13: Historic preference | I13: Core modification | J13: Retired | K13: Order management | L13: Market | M13: 18 | N13: 11000 | O13: 46138 | P13: =IF(O13="","",O13-Settings!$B$2) | Q13: =IF(B13="",0,Settings!$B$2-B13) | R13: Replaced by the standard once release 2026 moved the check - the vendor caught up
A14: EXT-013 | B14: 45960 | C14: Market D | D14: P. Almeida | E14: Local promotion pricing sheet integration | F14: No interface to the local sheet | G14: Prices maintained twice | H14: Historic preference | I14: Side-by-side | J14: Bought out | K14: Pricing architect | L14: Central | M14: 22 | N14: 10000 | P14: =IF(O14="","",O14-Settings!$B$2) | Q14: =IF(B14="",0,Settings!$B$2-B14) | R14: Third market to ask - taken over centrally, local copies retired
P15: =IF(O15="","",O15-Settings!$B$2) | Q15: =IF(B15="",0,Settings!$B$2-B15)
P16: =IF(O16="","",O16-Settings!$B$2) | Q16: =IF(B16="",0,Settings!$B$2-B16)
P17: =IF(O17="","",O17-Settings!$B$2) | Q17: =IF(B17="",0,Settings!$B$2-B17)
P18: =IF(O18="","",O18-Settings!$B$2) | Q18: =IF(B18="",0,Settings!$B$2-B18)
P19: =IF(O19="","",O19-Settings!$B$2) | Q19: =IF(B19="",0,Settings!$B$2-B19)
P20: =IF(O20="","",O20-Settings!$B$2) | Q20: =IF(B20="",0,Settings!$B$2-B20)
P21: =IF(O21="","",O21-Settings!$B$2) | Q21: =IF(B21="",0,Settings!$B$2-B21)
P22: =IF(O22="","",O22-Settings!$B$2) | Q22: =IF(B22="",0,Settings!$B$2-B22)
P23: =IF(O23="","",O23-Settings!$B$2) | Q23: =IF(B23="",0,Settings!$B$2-B23)
P24: =IF(O24="","",O24-Settings!$B$2) | Q24: =IF(B24="",0,Settings!$B$2-B24)
P25: =IF(O25="","",O25-Settings!$B$2) | Q25: =IF(B25="",0,Settings!$B$2-B25)
P26: =IF(O26="","",O26-Settings!$B$2) | Q26: =IF(B26="",0,Settings!$B$2-B26)
... P251: =IF(O251="","",O251-Settings!$B$2) | Q251: =IF(B251="",0,Settings!$B$2-B251)

Sheet Interfaces
A1: Int ID | B1: Name | C1: Source | D1: Target | E1: Object | F1: Pattern | G1: Direction | H1: Contract | I1: Sync/Async | J1: Idempotent | K1: Replayable | L1: Owner | M1: Bridge expiry | N1: Days to expiry | O1: Notes
A2: INT-001 | B2: Supplier master to market portal | C2: Core | D2: Portal B | E2: Supplier | F2: Event | G2: Outbound | H2: Released | I2: Async | J2: Yes | K2: Yes | L2: Integration team | N2: =IF(M2="","",M2-Settings!$B$2) | O2: Canonical supplier shape; dialect translated at the portal edge
A3: INT-002 | B3: Sales orders from web shop | C3: Shop | D3: Core | E3: Sales order | F3: API | G3: Inbound | H3: Released | I3: Async | J3: Yes | K3: Yes | L3: Integration team | N3: =IF(M3="","",M3-Settings!$B$2) | O3: Idempotency key is the shop order reference
A4: INT-003 | B4: Stock levels to planning tool | C4: Core | D4: Planning | E4: Stock | F4: Event | G4: Outbound | H4: Released | I4: Async | J4: Yes | K4: Yes | L4: Supply chain IT | N4: =IF(M4="","",M4-Settings!$B$2)
A5: INT-004 | B5: Legacy pricing feed | C5: Core | D5: Pricing legacy | E5: Price | F5: File | G5: Outbound | H5: Bridge - expiry set | I5: Async | J5: No | K5: No | L5: Pricing architect | M5: 46295 | N5: =IF(M5="","",M5-Settings!$B$2) | O5: No schema when inherited; schema added, dead-letter added, owner named
A6: INT-005 | B6: Local supplier register lookup | C6: Side-by-side | D6: Core | E6: Supplier | F6: API | G6: Both | H6: Released | I6: Sync | J6: Yes | K6: No | L6: Integration team | N6: =IF(M6="","",M6-Settings!$B$2) | O6: User is waiting, so synchronous is justified
A7: INT-006 | B7: Warehouse confirmations | C7: WMS | D7: Core | E7: Goods movement | F7: API | G7: Inbound | H7: Released | I7: Async | J7: Yes | K7: Yes | L7: Logistics IT | N7: =IF(M7="","",M7-Settings!$B$2)
A8: INT-007 | B8: HR org data | C8: HR system | D8: Core | E8: Employee | F8: Event | G8: Inbound | H8: Released | I8: Async | J8: Yes | K8: Yes | L8: HR IT | N8: =IF(M8="","",M8-Settings!$B$2)
A9: INT-008 | B9: Reporting extract | C9: Core | D9: Data platform | E9: Multiple | F9: API | G9: Outbound | H9: Released | I9: Async | J9: Yes | K9: Yes | L9: Data platform | N9: =IF(M9="","",M9-Settings!$B$2) | O9: Replaced a direct database read in Q1
A10: INT-009 | B10: Market C statutory export | C10: Core | D10: Tax filing | E10: Journal | F10: File | G10: Outbound | H10: Released | I10: Async | J10: Yes | K10: Yes | L10: Localization lead | N10: =IF(M10="","",M10-Settings!$B$2) | O10: Built once in the localization layer, reused by two markets
A11: INT-010 | B11: Old finance interface | C11: Core | D11: Finance legacy | E11: Journal | F11: Direct DB | G11: Outbound | H11: Unreleased | I11: Sync | J11: No | K11: No | L11: Finance IT | M11: 46265 | N11: =IF(M11="","",M11-Settings!$B$2) | O11: Being replaced by INT-008; counted as a forbidden pattern until it is off
N12: =IF(M12="","",M12-Settings!$B$2)
N13: =IF(M13="","",M13-Settings!$B$2)
N14: =IF(M14="","",M14-Settings!$B$2)
N15: =IF(M15="","",M15-Settings!$B$2)
N16: =IF(M16="","",M16-Settings!$B$2)
N17: =IF(M17="","",M17-Settings!$B$2)
N18: =IF(M18="","",M18-Settings!$B$2)
N19: =IF(M19="","",M19-Settings!$B$2)
N20: =IF(M20="","",M20-Settings!$B$2)
N21: =IF(M21="","",M21-Settings!$B$2)
N22: =IF(M22="","",M22-Settings!$B$2)
N23: =IF(M23="","",M23-Settings!$B$2)
... N201: =IF(M201="","",M201-Settings!$B$2)

Sheet Ownership
A1: Object | B1: Master system | C1: Consumers | D1: Contract out | E1: Contract in | F1: Owner | G1: Contested? | H1: Note
A2: Supplier | B2: Core | C2: Portal B, side-by-side register, data platform | D2: Event | E2: API | F2: Procurement IT | G2: No | H2: Settled Q3 last year after two systems both updating bank details
A3: Customer | B3: CRM | C3: Core, web shop, data platform | D3: Event | E3: API | F3: Sales IT | G3: No
A4: Material | B4: Core | C4: WMS, planning, shop | D4: Event | E4: API | F4: Supply chain IT | G4: No
A5: Price | B5: Core | C5: Shop, portal | D5: API | E5: - | F5: Pricing architect | G5: Yes | H5: Side-by-side pricing service will take mastership in Q4 - decision recorded
A6: Employee | B6: HR system | C6: Core, access management | D6: Event | E6: - | F6: HR IT | G6: No
A7: Sales order | B7: Core | C7: Data platform, WMS | D7: Event | E7: API | F7: Order management | G7: No
A8: Stock | B8: Core | C8: Planning, shop | D8: Event | E8: - | F8: Supply chain IT | G8: No
A9: Journal | B9: Core | C9: Tax filing, data platform | D9: File, API | E9: - | F9: Finance IT | G9: No | H9: Legacy direct read being retired - see INT-010

Sheet Buy-out candidates
A1: Buy-out candidates
A2: Paste a distinct need into column A. The count is computed across the Extensions sheet; anything at or above the threshold on Settings is a candidate.
A4: Need (as written in Extensions) | B4: Markets | C4: Candidate? | D4: What central does about it
A5: Local supplier register check at goods receipt | B5: =IF($A5="","",SUMPRODUCT((Extensions!$E$2:$E$251=$A5)*(Extensions!$C$2:$C$251<>""))) | C5: =IF($A5="","",IF(B5>=Settings!$B$4,"YES","-")) | D5: Build once side-by-side, fund centrally, retire the three local copies
A6: Statutory e-invoice layout | B6: =IF($A6="","",SUMPRODUCT((Extensions!$E$2:$E$251=$A6)*(Extensions!$C$2:$C$251<>""))) | C6: =IF($A6="","",IF(B6>=Settings!$B$4,"YES","-")) | D6: Already central - localization layer, built once per requirement
A7: Screen field added for local contract reference | B7: =IF($A7="","",SUMPRODUCT((Extensions!$E$2:$E$251=$A7)*(Extensions!$C$2:$C$251<>""))) | C7: =IF($A7="","",IF(B7>=Settings!$B$4,"YES","-")) | D7: Below threshold; revisit if a third market asks
A8: Custom pricing condition in the core | B8: =IF($A8="","",SUMPRODUCT((Extensions!$E$2:$E$251=$A8)*(Extensions!$C$2:$C$251<>""))) | C8: =IF($A8="","",IF(B8>=Settings!$B$4,"YES","-")) | D8: Replace with the side-by-side pricing service, then close the modification
B9: =IF($A9="","",SUMPRODUCT((Extensions!$E$2:$E$251=$A9)*(Extensions!$C$2:$C$251<>""))) | C9: =IF($A9="","",IF(B9>=Settings!$B$4,"YES","-"))

Sheet Scorecard
A1: The four numbers
A2: Reported monthly, to named people, with the specific items rather than only the totals.
A4: Core modifications, open | B4: =COUNTIFS(Extensions!$I$2:$I$251,"Core modification",Extensions!$J$2:$J$251,"<>Retired",Extensions!$J$2:$J$251,"<>Bought out",Extensions!$J$2:$J$251,"<>Rejected") | C4: The temperature. Counted, with the trend, named in the register. Catches the quiet return of the old habit
A5: Core modifications closed this year | B5: =COUNTIFS(Extensions!$I$2:$I$251,"Core modification",Extensions!$J$2:$J$251,"Retired") | C5: Effort, made visible. Without it the first number only ever looks like an accusation
A6: Interfaces on released contracts | B6: =IF(COUNTA(Interfaces!$A$2:$A$201)=0,"",COUNTIF(Interfaces!$H$2:$H$201,"Released")/COUNTA(Interfaces!$A$2:$A$201)) | C6: The plumbing. The rest are bridges, each with an expiry date. Catches direct database reads accumulating unseen
A7: Interfaces on forbidden patterns | B7: =COUNTIF(Interfaces!$F$2:$F$201,"Direct DB")+COUNTIF(Interfaces!$H$2:$H$201,"Unreleased") | C7: Direct DB and point-to-point with no contract. This number should be shrinking every quarter or the standard is not real
A8: Open register items | B8: =COUNTIFS(Extensions!$A$2:$A$251,"<>",Extensions!$I$2:$I$251,"<>Configuration",Extensions!$J$2:$J$251,"<>Retired",Extensions!$J$2:$J$251,"<>Bought out",Extensions!$J$2:$J$251,"<>Rejected") | C8: The leading indicator. A register that only grows is a triage that stopped working
A9: Oldest open item (days) | B9: =SUMPRODUCT(MAX((Extensions!$A$2:$A$251<>"")*(Extensions!$I$2:$I$251<>"Configuration")*(Extensions!$J$2:$J$251<>"Retired")*(Extensions!$J$2:$J$251<>"Bought out")*(Extensions!$J$2:$J$251<>"Rejected")*Extensions!$Q$2:$Q$251)) | C9: The age is the story. A young register of forty items is healthier than an old one of twelve
A10: Items expiring within the warning window | B10: =COUNTIFS(Extensions!$P$2:$P$251,"<="&Settings!$B$5,Extensions!$P$2:$P$251,">=-3650") | C10: The quarterly review's agenda, computed
A11: Upgrade lead time (days, rehearsed) | C11: The only honest measure. A programme that has never rehearsed an upgrade does not know whether its core is clean - it knows whether its rules were followed, which is not the same thing
A14: Rehearse the upgrade while the programme still has budget and attention. It is the measure that cannot be faked.

Sheet Trend
A1: Month | B1: Core mods open | C1: Mods closed | D1: Released contract % | E1: Forbidden patterns | F1: Open register | G1: Oldest (days) | H1: Upgrade lead time
A2: 2025-09 | B2: 21 | C2: 0 | D2: 0.62 | E2: 9 | F2: 18 | G2: 140
A3: 2025-12 | B3: 18 | C3: 3 | D3: 0.71 | E3: 7 | F3: 24 | G3: 190 | H3: 42
A4: 2026-03 | B4: 15 | C4: 6 | D4: 0.79 | E4: 5 | F4: 29 | G4: 205 | H4: 21
A5: 2026-06 | B5: 12 | C5: 10 | D5: 0.84 | E5: 3 | F5: 31 | G5: 214 | H5: 9
A34: Example figures. Replace them - the point is the shape over twelve months, not the level in any one.
