Workbook

Sheet Read me
A1: Decision and register workbook
A2: Four registers on one shared shape, plus the links that make records surface later and the derived views that tell you whether the practice is working.
A4: The shape, in every register
A5: Chose, Rejected, Why, Cost we accept - plus ID, date, decider, status, and links. If two registers use different shapes nobody can read across them, and reading across them is where the value compounds.
A7: Why four registers rather than one
A8: Because the clocks differ. Directions run until superseded, exceptions expire on a date, assessments refresh on a cycle, classifications hold until the underlying fact changes. A register whose entries expire on four clocks cannot be reviewed as one thing.
A10: The sheets
A11: Decisions - directions, selections and dispositions. The main log.
A12: Exceptions - permitted violations, each with an expiry and a closure condition.
A13: Classifications - values set on repository records, with the rationale that is normally lost.
A14: Assessments - judgements at a point in time, with the rater, the anchor cited, and the next cycle.
A15: Links - one flat table joining any record to the applications, objects, domains, interfaces and projects it touches.
... A30: Companion article: mehdibamou.com/publications/decision-records - free to use and adapt

Sheet Settings
A1: Setting | B1: Value | C1: Note
A2: As-at date | B2: 46254 | C2: Drives expiry countdowns and staleness
A3: Warn before expiry (days) | B3: 60 | C3: How early a record shows as due
A4: Assessment cycle (months) | B4: 6 | C4: After this an assessment is stale
A5: Repetition threshold | B5: 3 | C5: Same topic this many times means a missing principle

Sheet Lists
A1: Direction | B1: Proposed | C1: Open | D1: Application | E1: Business fit
A2: Selection | B2: Accepted | C2: Closed | D2: IT component | E2: Technical fit
A3: Disposition | B3: Superseded | C3: Extended | D3: Object | E3: Capability maturity
B4: Rejected | C4: Expired | D4: Domain | E4: Data quality
D5: Interface
D6: Project
D7: Capability

Sheet Decisions
A1: ID | B1: Kind | C1: Date | D1: Decided by | E1: Topic | F1: Chose | G1: Rejected | H1: Why | I1: Cost we accept | J1: Status | K1: Supersedes | L1: Superseded by | M1: Review date | N1: Days to review
A2: ADR-018 | B2: Direction | C2: 45203 | D2: Design forum | E2: Price mastership | F2: Price is mastered by the commerce platform | G2: Mastering price in the core, which nobody wanted to configure at the time | H2: Commerce was the only system with a pricing screen and the core rollout had not started | I2: The core consumes price from commerce, which reverses the usual direction | J2: Superseded | L2: ADR-041 | N2: =IF(M2="","",M2-Settings!$B$2)
A3: ADR-041 | B3: Direction | C3: 45608 | D3: Architecture board | E3: Price mastership | F3: Price is mastered by the core | G3: A separate pricing engine, judged premature with one market live | H3: Only one market was live and the condition technique covered the rules then | I3: Pricing rules stay within what the standard can express | J3: Superseded | K3: ADR-018 | L3: ADR-092 | N3: =IF(M3="","",M3-Settings!$B$2)
A4: ADR-063 | B4: Direction | C4: 45841 | D4: Architecture board | E4: Core integration | F4: Every interface to the core uses a released API or event | G4: Direct table reads, which two existing interfaces already used | H4: Two direct reads built in 2022 broke the last upgrade and cost a weekend | I4: Some interfaces wait for the vendor to publish an API | J4: Accepted | N4: =IF(M4="","",M4-Settings!$B$2)
A5: ADR-071 | B5: Direction | C5: 46035 | D5: Architecture board | E5: Customer copies | F5: Campaign tool reads customer via API and holds no authoritative copy | G5: A local customer store, which would have shipped the campaign three weeks earlier | H5: Three of last year's four data incidents came from two systems owning one object | I5: The campaign shipped two weeks later than hoped | J5: Accepted | N5: =IF(M5="","",M5-Settings!$B$2)
A6: ADR-088 | B6: Direction | C6: 46049 | D6: Design forum | E6: Event broker | F6: Defer the broker choice until a second producer exists | G6: Choosing now on one producer and a proof of concept | H6: A single producer does not exercise load, replay or operability | I6: First producer ships on the existing queue and will migrate, roughly two weeks of rework | J6: Accepted | M6: 46295 | N6: =IF(M6="","",M6-Settings!$B$2)
A7: ADR-092 | B7: Direction | C7: 46182 | D7: Architecture board | E7: Price mastership | F7: Price becomes mastered by the side-by-side pricing service from the Q4 cutover | G7: Extending the condition technique in the core. Mastering price in commerce, dismissed because commerce consumes every other object | H7: The rules the business needs cannot be expressed without a core modification, and we are counting those down | I7: Eight weeks of dual write and a reconciliation nobody wants to run | J7: Accepted | K7: ADR-041 | N7: =IF(M7="","",M7-Settings!$B$2)
A8: SEL-07 | B8: Selection | C8: 46099 | D8: Steering committee | E8: Warehouse system, market D | F8: Vendor B | G8: Vendor A, excluded on mandatory M-1 (cannot operate against externally mastered data, demonstrated live). Vendor C withdrew at shortlist | H8: B met all three mandatory criteria; the commercial gap was decisive and the architecture gap judged recoverable through configuration | I8: B publishes events by polling. We accept latency on stock updates, written into the contract | J8: Accepted | M8: 47210 | N8: =IF(M8="","",M8-Settings!$B$2)
A9: DSP-22 | B9: Disposition | C9: 46148 | D9: Domain architect | E9: Market F picking sequence | F9: Fit-gap list with a twelve-month review | G9: Building it side-by-side, or a core modification | H9: No legal basis and no group need. The warehouse layout predates the standard | I9: Market F retrains staff on the standard sequence | J9: Accepted | M9: 46513 | N9: =IF(M9="","",M9-Settings!$B$2)
N10: =IF(M10="","",M10-Settings!$B$2)
N11: =IF(M11="","",M11-Settings!$B$2)
N12: =IF(M12="","",M12-Settings!$B$2)
N13: =IF(M13="","",M13-Settings!$B$2)
N14: =IF(M14="","",M14-Settings!$B$2)
N15: =IF(M15="","",M15-Settings!$B$2)
N16: =IF(M16="","",M16-Settings!$B$2)
N17: =IF(M17="","",M17-Settings!$B$2)
N18: =IF(M18="","",M18-Settings!$B$2)
N19: =IF(M19="","",M19-Settings!$B$2)
N20: =IF(M20="","",M20-Settings!$B$2)
N21: =IF(M21="","",M21-Settings!$B$2)
... N301: =IF(M301="","",M301-Settings!$B$2)

Sheet Exceptions
A1: ID | B1: Raised | C1: Deviates from | D1: Why | E1: Approved by | F1: Owner | G1: Expiry | H1: Days to expiry | I1: Renewals | J1: New reason on last renewal? | K1: Closure condition | L1: Status | M1: Closed
A2: EXC-09 | B2: 45565 | C2: No local supplier stores outside the core and the two registered registers | D2: Six-month workaround pending the onboarding service | E2: Architecture board | F2: Procurement IT | G2: 46112 | H2: =IF(OR(G2="",L2="Closed"),"",G2-Settings!$B$2) | I2: 2 | J2: No | K2: Onboarding service live in this market | L2: Closed | M2: 46215
A3: EXC-10 | B3: 46084 | C3: Contract data held only in the core | D3: Residency requirement, statutory | E3: Compliance lead | F3: Legal IT | H3: =IF(OR(G3="",L3="Closed"),"",G3-Settings!$B$2) | I3: 0 | J3: - | K3: Permanent - statutory | L3: Open
A4: EXC-11 | B4: 46182 | C4: One system of record per object (P-01) | D4: Cutover requires dual write for eight weeks | E4: Architecture board | F4: Named architect | G4: 46380 | H4: =IF(OR(G4="",L4="Closed"),"",G4-Settings!$B$2) | I4: 0 | J4: - | K4: Old write path off, confirmed by the object owner | L4: Open
A5: EXC-12 | B5: 45874 | C5: Promotion mastered in the core | D5: Tool predates the programme; migration in wave three | E5: Architecture board | F5: Marketing IT | G5: 46142 | H5: =IF(OR(G5="",L5="Closed"),"",G5-Settings!$B$2) | I5: 1 | J5: Yes | K5: Wave three complete | L5: Open
A6: EXC-13 | B6: 46070 | C6: Every interface uses a released contract (ADR-063) | D6: Vendor has not published the API; bridge in place | E6: Design forum | F6: Integration team | G6: 46295 | H6: =IF(OR(G6="",L6="Closed"),"",G6-Settings!$B$2) | I6: 0 | J6: - | K6: Vendor API published and consumed | L6: Open
H7: =IF(OR(G7="",L7="Closed"),"",G7-Settings!$B$2)
H8: =IF(OR(G8="",L8="Closed"),"",G8-Settings!$B$2)
H9: =IF(OR(G9="",L9="Closed"),"",G9-Settings!$B$2)
H10: =IF(OR(G10="",L10="Closed"),"",G10-Settings!$B$2)
H11: =IF(OR(G11="",L11="Closed"),"",G11-Settings!$B$2)
H12: =IF(OR(G12="",L12="Closed"),"",G12-Settings!$B$2)
H13: =IF(OR(G13="",L13="Closed"),"",G13-Settings!$B$2)
H14: =IF(OR(G14="",L14="Closed"),"",G14-Settings!$B$2)
H15: =IF(OR(G15="",L15="Closed"),"",G15-Settings!$B$2)
H16: =IF(OR(G16="",L16="Closed"),"",G16-Settings!$B$2)
H17: =IF(OR(G17="",L17="Closed"),"",G17-Settings!$B$2)
H18: =IF(OR(G18="",L18="Closed"),"",G18-Settings!$B$2)
... H201: =IF(OR(G201="",L201="Closed"),"",G201-Settings!$B$2)
A203: An extension without a new reason is a rejection with better manners. Column J is the tell that the quarterly review has stopped happening.

Sheet Classifications
A1: ID | B1: Date | C1: Record | D1: Record type | E1: Field set | F1: Chose | G1: Rejected | H1: Why | I1: Cost we accept | J1: Decided by | K1: Review trigger
A2: CLS-014 | B2: 46064 | C2: APP-077 | D2: Application | E2: Application or IT component | F2: One application | G2: Three IT components under a notional parent | H2: Business users interact with it directly, which is the line we apply everywhere. The parts have no independent lifecycle and no separate owner | I2: Per-part end-of-support reporting moves to a note on the record | J2: Portfolio owner | K2: When the semantic layer is replaced
A3: CLS-015 | B3: 46085 | C3: OBJ-04 | D3: Object | E3: Definition boundary | F3: A supplier is a legal entity we can raise a purchase order against | G3: Including carriers and one-off payees, as finance wanted | H3: Carriers have a different lifecycle and different statutory handling | I3: Finance keeps a separate payee list and reconciles monthly | J3: Data steward | K3: If the payment process changes
A4: CLS-016 | B4: 46134 | C4: APP-118 | D4: Application | E4: Lifecycle and sunset | F4: Phase-out with sunset 2027-06-30 | G4: Retain, which the market argued for | H4: The onboarding service covers the capability from wave two, and the licence renews in 2027 | I4: The market runs both for one quarter during transition | J4: Application owner | K4: At wave two go-live
A5: CLS-017 | B5: 46161 | C5: OBJ-01 | D5: Object | E5: Residency classification | F5: Customer data for markets B, E and G stays in-country | G5: One EU region for all markets, which is cheaper | H5: Three markets have statutory residency requirements naming the jurisdiction | I5: Three additional database instances and their operating cost | J5: Compliance lead | K5: On any new market
A303: The register almost nobody keeps. These are the calls that change counts, ownership and budgets for years, and they are normally recorded nowhere.

Sheet Assessments
A1: ID | B1: Date | C1: Record | D1: Scale | E1: Chose | F1: Rejected | G1: Anchor cited | H1: Why | I1: Rated by | J1: Disputed? | K1: Next cycle | L1: Days since
A2: ASM-2026-Q2-APP-118 | B2: 46146 | C2: APP-118 | D2: Business fit | E2: 2 | F2: 3 | G2: "Does the job with accepted workarounds" is the anchor for 3 | H2: Two of four core steps are done outside the system in a spreadsheet maintained by one person. A core gap filled by a shadow tool is the published anchor for 2 | I2: Head of procurement ops | J2: Yes | K2: 46330 | L2: =IF(B2="",0,Settings!$B$2-B2)
A3: ASM-2026-Q2-APP-118T | B3: 46146 | C3: APP-118 | D3: Technical fit | E3: 2 | G3: "Components approaching end of support" is the anchor for 2 | H3: The database version is out of support in eleven months and the integration is a file drop with no schema | I3: Integration team | J3: No | K3: 46330 | L3: =IF(B3="",0,Settings!$B$2-B3)
A4: ASM-2026-Q2-APP-002 | B4: 46153 | C4: APP-002 | D4: Business fit | E4: 3 | G4: "Does the job with accepted workarounds" | H4: Two markets maintain parallel spreadsheets for reporting, accepted and understood | I4: Head of order management | J4: No | K4: 46337 | L4: =IF(B4="",0,Settings!$B$2-B4)
A5: ASM-2025-Q4-APP-070 | B5: 45979 | C5: APP-070 | D5: Technical fit | E5: 2 | F5: 3 | G5: "Integration debt accumulating" | H5: Three point-to-point interfaces with no contracts, all built in one quarter | I5: Integration team | J5: No | K5: 46160 | L5: =IF(B5="",0,Settings!$B$2-B5)
L6: =IF(B6="",0,Settings!$B$2-B6)
L7: =IF(B7="",0,Settings!$B$2-B7)
L8: =IF(B8="",0,Settings!$B$2-B8)
L9: =IF(B9="",0,Settings!$B$2-B9)
L10: =IF(B10="",0,Settings!$B$2-B10)
L11: =IF(B11="",0,Settings!$B$2-B11)
L12: =IF(B12="",0,Settings!$B$2-B12)
L13: =IF(B13="",0,Settings!$B$2-B13)
L14: =IF(B14="",0,Settings!$B$2-B14)
L15: =IF(B15="",0,Settings!$B$2-B15)
L16: =IF(B16="",0,Settings!$B$2-B16)
L17: =IF(B17="",0,Settings!$B$2-B17)
... L301: =IF(B301="",0,Settings!$B$2-B301)

Sheet Links
A1: Link ID | B1: Record ID | C1: Register | D1: Linked type | E1: Linked ID | F1: Linked name | G1: Note
A2: L-001 | B2: ADR-092 | C2: Decisions | D2: Object | E2: OBJ-07 | F2: Price
A3: L-002 | B3: ADR-092 | C3: Decisions | D3: Application | E3: APP-002 | F3: Core ERP | G3: loses mastership
A4: L-003 | B4: ADR-092 | C4: Decisions | D4: Application | E4: APP-131 | F4: Pricing service | G4: gains mastership
A5: L-004 | B5: ADR-092 | C5: Decisions | D5: Domain | E5: DOM-05 | F5: Pricing and promotion
A6: L-005 | B6: EXC-11 | C6: Exceptions | D6: Object | E6: OBJ-07 | F6: Price | G6: dual write window
A7: L-006 | B7: ADR-063 | C7: Decisions | D7: Interface | E7: INT-010 | F7: Old finance interface | G7: the one this decision forbids
A8: L-007 | B8: ADR-063 | C8: Decisions | D8: Domain | E8: DOM-10 | F8: Corporate platforms
A9: L-008 | B9: ADR-071 | C9: Decisions | D9: Object | E9: OBJ-01 | F9: Customer
A10: L-009 | B10: ADR-071 | C10: Decisions | D10: Application | E10: APP-090 | F10: Campaign tool
A11: L-010 | B11: CLS-014 | C11: Classifications | D11: Application | E11: APP-077 | F11: Data platform
A12: L-011 | B12: CLS-017 | C12: Classifications | D12: Object | E12: OBJ-01 | F12: Customer | G12: residency
A13: L-012 | B13: CLS-017 | C13: Classifications | D13: IT component | E13: ITC-052 | F13: Market G database, in-country
A14: L-013 | B14: SEL-07 | C14: Decisions | D14: Project | E14: PRJ-0426 | F14: Replace the market D warehouse system
A15: L-014 | B15: SEL-07 | C15: Decisions | D15: Application | E15: APP-119 | F15: Market D warehouse system
A16: L-015 | B16: EXC-09 | C16: Exceptions | D16: Project | E16: PRJ-0418 | F16: Supplier onboarding for market D | G16: the project that closed it
A17: L-016 | B17: EXC-09 | C17: Exceptions | D17: Object | E17: OBJ-04 | F17: Supplier
A18: L-017 | B18: ASM-2026-Q2-APP-118 | C18: Assessments | D18: Application | E18: APP-118 | F18: Market D supplier register
A19: L-018 | B19: DSP-22 | C19: Decisions | D19: Domain | E19: DOM-06 | F19: Logistics
A20: L-019 | B20: DSP-22 | C20: Decisions | D20: Application | E20: APP-119 | F20: Market D warehouse system
A21: L-020 | B21: ADR-088 | C21: Decisions | D21: Domain | E21: DOM-10 | F21: Corporate platforms
A22: L-021 | B22: ADR-088 | C22: Decisions | D22: Interface | E22: INT-060 | F22: Customer events, first producer
A23: L-022 | B23: ADR-018 | C23: Decisions | D23: Object | E23: OBJ-07 | F23: Price
A24: L-023 | B24: ADR-041 | C24: Decisions | D24: Object | E24: OBJ-07 | F24: Price
A402: Without these rows a record is findable only by somebody who already knows it exists - which is exactly the person who does not need it.

Sheet Derived views
A1: Is the practice actually working
A2: Nothing here is typed. Read it monthly; the repetition counter is the one that pays.
A4: Decisions recorded | B4: =COUNTA(Decisions!$A$2:$A$301) | D4: The base number
A5: Decisions missing the Rejected field | B5: =COUNTIFS(Decisions!$A$2:$A$301,"<>",Decisions!$G$2:$G$301,"") | C5: should be 0 | D5: The most common failure. Without it the argument returns
A6: Decisions missing the Cost field | B6: =COUNTIFS(Decisions!$A$2:$A$301,"<>",Decisions!$I$2:$I$301,"") | C6: should be 0 | D6: A decision with no stated cost was a preference
A7: Decisions with no links | B7: =SUMPRODUCT((Decisions!$A$2:$A$301<>"")*(COUNTIF(Links!$B$2:$B$400,Decisions!$A$2:$A$301)=0)) | C7: should be 0 | D7: These will never surface in an impact list
A8: Superseded decisions with no forward pointer | B8: =COUNTIFS(Decisions!$J$2:$J$301,"Superseded",Decisions!$L$2:$L$301,"") | C8: should be 0 | D8: The trail breaks here
A9: Open exceptions | B9: =COUNTIF(Exceptions!$L$2:$L$201,"Open") | D9: The register's temperature
A10: Open exceptions past expiry | B10: =COUNTIFS(Exceptions!$L$2:$L$201,"Open",Exceptions!$H$2:$H$201,"<0") | C10: should be 0 | D10: The quarterly review did not happen
A11: Open exceptions due within the warning window | B11: =COUNTIFS(Exceptions!$L$2:$L$201,"Open",Exceptions!$H$2:$H$201,"<="&Settings!$B$3,Exceptions!$H$2:$H$201,">=0") | D11: This quarter's agenda, computed
A12: Exceptions renewed with no new reason | B12: =COUNTIFS(Exceptions!$J$2:$J$201,"No") | C12: should be 0 | D12: An extension without a new reason is a rejection with better manners
A13: Classifications recorded | B13: =COUNTA(Classifications!$A$2:$A$301) | D13: The register almost nobody keeps
A14: Assessments past their cycle | B14: =COUNTIFS(Assessments!$A$2:$A$301,"<>",Assessments!$L$2:$L$301,">"&Settings!$B$4*31) | D14: Stale judgements still being quoted as current
A15: Disputed assessments | B15: =COUNTIF(Assessments!$J$2:$J$301,"Yes") | D15: Not a problem. It means the anchors are doing their job
A18: Repetition: the same topic arriving again and again
A19: Type a topic in the yellow cells. At or above the threshold on Settings, you are not looking at an annoyance - you are looking at a missing principle.
A20: Topic (as written in Decisions) | B20: Times decided | C20: Missing principle? | D20: What it is probably telling you
A21: Price mastership | B21: =IF($A21="","",COUNTIF(Decisions!$E$2:$E$301,$A21)) | C21: =IF($A21="","",IF(B21>=Settings!$B$5,"YES","-")) | D21: Three decisions in three years on one object. This is a missing principle about system of record, announcing itself
A22: Core integration | B22: =IF($A22="","",COUNTIF(Decisions!$E$2:$E$301,$A22)) | C22: =IF($A22="","",IF(B22>=Settings!$B$5,"YES","-")) | D22: A principle about released contracts, which you may already have
A23: Customer copies | B23: =IF($A23="","",COUNTIF(Decisions!$E$2:$E$301,$A23)) | C23: =IF($A23="","",IF(B23>=Settings!$B$5,"YES","-")) | D23: A principle about one system of record per object
B24: =IF($A24="","",COUNTIF(Decisions!$E$2:$E$301,$A24)) | C24: =IF($A24="","",IF(B24>=Settings!$B$5,"YES","-"))
B25: =IF($A25="","",COUNTIF(Decisions!$E$2:$E$301,$A25)) | C25: =IF($A25="","",IF(B25>=Settings!$B$5,"YES","-"))
A40: Every time-boxed record generates its own review agenda. The quarterly session does not need a facilitator deciding what to discuss - the register decides, by date.
