Workbook

Sheet Read me
A1: Joining workbook
A2: The first architect's working file: decisions in flight, workstreams, an interface-derived landscape, the impact notes you write, and the ninety-day plan.
A4: What this is | B4: A working file for the first ninety days in an organization where enterprise architecture is new: no principles, no object model, no catalogue, no forum. It is deliberately a spreadsheet. A tool business case in month one is a temptation, not a plan.
A5: Order of use | B5: 1. Decisions in flight, filled from reading the board in week one. 2. Workstreams, same week. 3. Interfaces, after the integration conversation. 4. Landscape, derived from Interfaces. 5. Impact notes, from the nearest irreversible decision. 6. Ninety days, to keep yourself honest.
A6: The rule behind it | B6: Start with the work in flight, not with the landscape. The landscape is what the work in flight is about to change, so the work tells you which part of the landscape matters.
A7: Stable IDs | B7: APP-001, INT-001, DEC-001, IMP-001. Never reuse a retired ID. This is the only thing at this stage that is expensive to get wrong, because everything you build later joins on these.
A8: Blank versus guess | B8: A blank owner is information. A guessed owner is a defect somebody will inherit and believe.
A9: Colour | B9: Amber cells are the ones you are expected to fill. Formulas are left visible on purpose - nothing here is hidden and you should change any of it.
A10: Companion | B10: The ninety-day pack (document) has the templates and the phrases. The worked artifacts deck shows a filled example of each output.
A11: Source | B11: mehdibamou.com/publications/joining-as-the-first-architect - free to use and adapt.

Sheet 1 Decisions in flight
A1: Decisions in flight
A2: Week one output. Read every workstream and the last thirty days of comments. Five is enough. Do not offer an opinion on any of them yet.
A4: ID | B4: Decision, as the project names it | C4: Workstream | D4: Who decides | E4: Decision by | F4: Reversible? | G4: Cost to unwind | H4: What it touches (first read) | I4: Do I have anything useful? | J4: Status
A5: DEC-001 | B5: Warehouse system replacement in one market: shortlist to one vendor | C5: Logistics reboot | D5: Market IT lead, with group CIO sign-off | E5: 2025-03-14 | F5: No | G5: High - contract, migration, feed rebuild | H5: Core stock movements, transport tool, data platform, market labelling tool | I5: Yes - nobody has costed the stock feed rebuild | J5: Note written
A6: DEC-002 | B6: Whether the new pricing service masters price or reads it | C6: Pricing platform | D6: Pricing product owner | E6: 2025-02-28 | F6: Partly | G6: Medium - rewrite of two consumers | H6: Pricing service, core, two market front ends | I6: Yes - two other markets consume the same feed | J6: Note written
A7: DEC-003 | B7: Customer identity: extend the existing directory or introduce a second | C7: Customer 360 | D7: Programme architect (vendor side) | E7: 2025-04-02 | F7: No | G7: High - duplicate mastering is permanent | H7: Directory, CRM, loyalty, three market apps | I7: Not yet - need the interface list first | J7: Watching
A8: DEC-004 | B8: Reporting: whether market extracts land in the platform or stay local | C8: Data platform | D8: Data lead | E8: 2025-03-21 | F8: Yes | G8: Low - re-point extracts | H8: Data platform, six market extracts | I8: No - team is better informed than I am | J8: Leave alone
A9: DEC-005 | B9: Retire or keep the legacy order tool after go-live in market two | C9: Logistics reboot | D9: Market operations manager | E9: 2025-05-30 | F9: Partly | G9: Medium - three integrations | H9: Legacy order tool, core, transport tool | I9: Yes - it is an endpoint on four interfaces | J9: Watching
A10: DEC-006
A11: DEC-007
A12: DEC-008
A42: Irreversible decisions still open: | D42: =COUNTIFS(F5:F40,"No",J5:J40,"<>Decided")
A43: Notes written: | D43: =COUNTIF(J5:J40,"Note written")
A45: If an irreversible decision is open and you have nothing useful, that is fine. If it is open and you do, the clock is running.

Sheet 2 Workstreams
A1: Workstream map
A2: From the board, in week one. The nouns matter more than the goals: which systems, which objects, which markets.
A4: ID | B4: Workstream | C4: Stated goal | D4: Systems named | E4: Objects touched | F4: Markets | G4: Project manager | H4: Delivery or vendor | I4: Build or buy | J4: Nearest decision | K4: Am I invited?
A5: WS-01 | B5: Logistics reboot | C5: Replace the warehouse system in two markets | D5: Warehouse system, core, transport tool | E5: Stock movement, shipment, location | F5: M1, M2 | G5: PM who invited me | H5: External vendor, shortlist of two | I5: Buy | J5: DEC-001 | K5: Yes
A6: WS-02 | B6: Pricing platform | C6: Central pricing service for all markets | D6: Pricing service, core, market front ends | E6: Price, promotion, product | F6: All | G6: Group PM | H6: Internal build team | I6: Build | J6: DEC-002 | K6: Partly
A7: WS-03 | B7: Customer 360 | C7: Single customer view across loyalty and CRM | D7: Directory, CRM, loyalty | E7: Customer, consent, loyalty account | F7: M1, M3, M4 | G7: Programme manager | H7: Vendor-led programme | I7: Buy | J7: DEC-003 | K7: No
A8: WS-04 | B8: Data platform | C8: Market reporting onto one platform | D8: Data platform, six market extracts | E8: Sales, stock, customer | F8: All | G8: Data lead | H8: Internal | I8: Build | J8: DEC-004 | K8: Yes
A9: WS-05 | B9: Store systems refresh | C9: Till and back-office hardware and software | D9: Till, back office, payments | E9: Transaction, payment, product | F9: M2 | G9: Market IT lead | H9: Mixed | I9: Buy | K9: No
A10: WS-06
A11: WS-07
A32: Workstreams I am not in: | D32: =COUNTIF(K5:K30,"No")
A33: A workstream you are not in is not a failure in month one. It is a target for month three. The route in is an impact note, not a request for access.

Sheet 3 Interfaces
A1: Interface list
A2: Ninety minutes with the person who maintains this beats six weeks of collection. Ask for the list, not the architecture.
A4: ID | B4: From | C4: To | D4: What moves (object) | E4: Direction | F4: Style | G4: Frequency | H4: Breaks often? | I4: Owner | J4: Would rebuild first? | K4: What they keep refusing
A5: INT-001 | B5: Core | C5: Warehouse system | D5: Stock movement | E5: One way | F5: Nightly file | G5: Daily | H5: Yes | I5: Integration team | J5: Yes | K5: Direct table reads into the core
A6: INT-002 | B6: Warehouse system | C6: Transport tool | D6: Shipment | E6: One way | F6: API | G6: Near real time | H6: No | I6: Integration team | J6: No
A7: INT-003 | B7: Core | C7: Data platform | D7: Sales, stock | E7: One way | F7: Batch extract | G7: Daily | H7: Sometimes | I7: Data lead | J7: No
A8: INT-004 | B8: Warehouse system | C8: Market labelling tool | D8: Product, location | E8: Two way | F8: Flat file on a share | G8: Hourly | H8: Yes | I8: Market IT (informal) | J8: Yes | K8: Anything that adds a new share-based feed
A9: INT-005 | B9: CRM | C9: Loyalty | D9: Customer, loyalty account | E9: Two way | F9: API | G9: Near real time | H9: No | I9: CRM team | J9: No
A10: INT-006 | B10: Directory | C10: CRM | D10: Customer identity | E10: One way | F10: Sync job | G10: Hourly | H10: Sometimes | I10: CRM team | J10: Yes | K10: A second place to master customer identity
A11: INT-007 | B11: Core | C11: Legacy order tool | D11: Order | E11: Two way | F11: Nightly file | G11: Daily | H11: Yes | I11: Integration team | J11: Yes
A12: INT-008 | B12: Pricing service | C12: Core | D12: Price | E12: One way | F12: API | G12: On change | H12: No | I12: Build team | J12: No | K12: Consumers writing prices back
A13: INT-009
A14: INT-010
A62: Interfaces listed: | D62: =COUNTIF(B5:B60,"?*")
A63: Breaking often: | D63: =COUNTIF(H5:H60,"Yes")
A64: Undocumented principles captured: | D64: =COUNTIF(K5:K60,"?*")
A66: Column K is where the organization's real rules already live. What the integration team keeps refusing, and why, is a principle nobody has written down yet.

Sheet 4 Landscape
A1: Landscape, scoped
A2: Derived from the interface list and the work in flight, plus one ring out. Not the architecture. The part of the landscape the current work touches.
A4: ID | B4: Application | C4: Business owner | D4: IT owner | E4: Markets | F4: In scope because | G4: Interfaces (count) | H4: Touched by workstream | I4: First seen | J4: Confidence
A5: APP-001 | B5: Core | C5: Group operations | D5: Core platform team | E5: All | F5: Endpoint on five interfaces in flight | G5: =COUNTIFS('3 Interfaces'!$B$5:$B$60,$B5)+COUNTIFS('3 Interfaces'!$C$5:$C$60,$B5) | H5: WS-01, WS-02, WS-04 | I5: 2025-01-13 | J5: High
A6: APP-002 | B6: Warehouse system | C6: Market M1 operations | D6: Market IT lead | E6: M1, M2 | F6: Being replaced under DEC-001 | G6: =COUNTIFS('3 Interfaces'!$B$5:$B$60,$B6)+COUNTIFS('3 Interfaces'!$C$5:$C$60,$B6) | H6: WS-01 | I6: 2025-01-13 | J6: High
A7: APP-003 | B7: Transport tool | C7: Market M1 operations | D7: Integration team | E7: M1, M2 | F7: Consumes shipment from the system being replaced | G7: =COUNTIFS('3 Interfaces'!$B$5:$B$60,$B7)+COUNTIFS('3 Interfaces'!$C$5:$C$60,$B7) | H7: WS-01 | I7: 2025-01-14 | J7: High
A8: APP-004 | B8: Data platform | D8: Data lead | E8: All | F8: One ring out from the core | G8: =COUNTIFS('3 Interfaces'!$B$5:$B$60,$B8)+COUNTIFS('3 Interfaces'!$C$5:$C$60,$B8) | H8: WS-04 | I8: 2025-01-14 | J8: Medium
A9: APP-005 | B9: Market labelling tool | E9: M1 | F9: Interface endpoint the project has not listed | G9: =COUNTIFS('3 Interfaces'!$B$5:$B$60,$B9)+COUNTIFS('3 Interfaces'!$C$5:$C$60,$B9) | H9: WS-01 | I9: 2025-01-16 | J9: Low
A10: APP-006 | B10: CRM | C10: Group marketing | D10: CRM team | E10: M1, M3, M4 | F10: In the Customer 360 scope | G10: =COUNTIFS('3 Interfaces'!$B$5:$B$60,$B10)+COUNTIFS('3 Interfaces'!$C$5:$C$60,$B10) | H10: WS-03 | I10: 2025-01-16 | J10: Medium
A11: APP-007 | B11: Loyalty | C11: Group marketing | D11: CRM team | E11: M1, M3 | F11: Two-way with CRM | G11: =COUNTIFS('3 Interfaces'!$B$5:$B$60,$B11)+COUNTIFS('3 Interfaces'!$C$5:$C$60,$B11) | H11: WS-03 | I11: 2025-01-16 | J11: Medium
A12: APP-008 | B12: Directory | D12: Platform team | E12: All | F12: Mastering question under DEC-003 | G12: =COUNTIFS('3 Interfaces'!$B$5:$B$60,$B12)+COUNTIFS('3 Interfaces'!$C$5:$C$60,$B12) | H12: WS-03 | I12: 2025-01-17 | J12: Low
A13: APP-009 | B13: Pricing service | C13: Group pricing | D13: Build team | E13: All | F13: Being built under WS-02 | G13: =COUNTIFS('3 Interfaces'!$B$5:$B$60,$B13)+COUNTIFS('3 Interfaces'!$C$5:$C$60,$B13) | H13: WS-02 | I13: 2025-01-17 | J13: High
A14: APP-010 | B14: Legacy order tool | C14: Market M2 operations | E14: M2 | F14: Retirement question under DEC-005 | G14: =COUNTIFS('3 Interfaces'!$B$5:$B$60,$B14)+COUNTIFS('3 Interfaces'!$C$5:$C$60,$B14) | H14: WS-01 | I14: 2025-01-20 | J14: Low
A15: APP-011
A16: APP-012
A42: Applications in scope: | D42: =COUNTIF(B5:B40,"?*")
A43: Missing an IT owner: | D43: =SUMPRODUCT((B5:B40<>"")*(D5:D40=""))
A44: Low confidence: | D44: =COUNTIF(J5:J40,"Low")
A46: Amber cells are missing owners. Leave them amber. A blank you can see is worth more than a name somebody guessed, and the amber is what you take to the next conversation.

Sheet 5 Impact notes
A1: Impact notes written
A2: One page each, to the project manager and the workstream lead. Nobody senior copied. No recommendation.
A4: ID | B4: Decision | C4: Date sent | D4: Sent to | E4: What it touches (beyond their list) | F4: Who else is affected | G4: What breaks | H4: What I would want to know | I4: Response | J4: Led to
A5: IMP-001 | B5: DEC-001 warehouse shortlist | C5: 2025-01-24 | D5: PM and market IT lead | E5: Market labelling tool (APP-005), not on the project list | F5: Two markets consuming the same stock feed | G5: Nightly file has no schema; both products expect events. Feed rebuild is in neither quote | H5: Whether either product can consume the file on the existing schedule during transition | I5: Forwarded to both vendors | J5: Invited to WS-03 in March
A6: IMP-002 | B6: DEC-002 pricing mastership | C6: 2025-02-05 | D6: Pricing product owner | E6: Two market front ends read price directly from the core | F6: Both markets, plus the data platform | G6: If pricing masters price without retiring the core write path, two systems master it | H6: Whether the core write path can be closed at cutover or has to stay open | I6: Discussed in their design session | J6: Write path added to their scope
A7: IMP-003
A8: IMP-004
A20: Notes sent: | D20: =COUNTIF(B5:B18,"?*")
A21: Notes that led somewhere: | D21: =COUNTIF(J5:J18,"?*")
A23: Column J is the only measure that matters in the first ninety days. A note that changed nothing is still fine. A run of six that changed nothing means you are writing reviews, not gifts.

Sheet 6 Decision log
A1: Decision log, backfilled
A2: Days 61 to 90. Write down what was already decided, before the discipline of writing down what is being decided.
A4: ID | B4: Title | C4: Decided on | D4: Decided by | E4: Status | F4: Context | G4: Decision | H4: Consequences accepted | I4: Where it lives | J4: Backfilled or live
A5: ADR-001 | B5: Stock movements master in the core | C5: 2023-06-00 (approx) | D5: Core platform team | E5: Accepted | F5: Two systems were writing stock; reconciliation was manual | G5: The core masters stock movement; everything else reads | H5: Warehouse changes need a core release | I5: Team drive, this file | J5: Backfilled
A6: ADR-002 | B6: No direct table reads into the core | C6: 2022-00-00 (approx) | D6: Integration team | E6: Accepted | F6: A reporting tool read tables directly and broke on every upgrade | G6: All access through published interfaces | H6: Some consumers wait for an interface to be built | I6: This file | J6: Backfilled
A7: ADR-003 | B7: Customer identity masters in the directory | C7: 2024-11-00 (approx) | D7: Platform team | E7: Contested | F7: CRM and the directory both hold identity; nobody wrote the rule down | G7: Directory masters; CRM holds a reference | H7: Contested by the Customer 360 programme - see DEC-003 | I7: This file | J7: Backfilled
A8: ADR-004 | B8: Warehouse replacement scope excludes labelling | C8: 2025-02-11 | D8: Market IT lead | E8: Accepted | F8: Labelling tool is a market-owned interface endpoint | G8: Labelling stays; the interface is rebuilt in wave two | H8: Wave two carries a dependency and a cost | I8: This file | J8: Live
A9: ADR-005
A42: Records: | D42: =COUNTIF(B5:B40,"?*")
A43: Backfilled: | D43: =COUNTIF(J5:J40,"Backfilled")
A44: Contested: | D44: =COUNTIF(E5:E40,"Contested")
A46: Eight to ten backfilled records is the target by day ninety. A contested record is the most valuable kind: it names a disagreement that was previously invisible and was being re-argued quietly.

Sheet 7 Ninety days
A1: The ninety-day plan
A2: Six phases. One output each, and one thing you deliberately do not do. Tick the output, not the activity.
A4: Phase | B4: Days | C4: Do | D4: Output | E4: Done? | F4: Date done | G4: Do not | H4: Evidence it landed
A5: Orientation | B5: 1-5 | C5: Read every workstream, epic, and the last thirty days of comments. One conversation with the PM who invited you | D5: A private list of five decisions in flight | G5: Offer an opinion in week one, however obvious the problem seems
A6: First gift | B6: 6-15 | C6: Write an impact note on the nearest irreversible decision | D6: One page, to the PM and the workstream lead | G6: Copy anyone senior. It stops being a gift and becomes a report
A7: Integration | B7: 16-30 | C7: Ask the integration team for the interface list, not the architecture | D7: A landscape sketch derived from interfaces | G7: Ask them to fill in a template. You are not collecting yet
A8: Scoped as-is | B8: 31-45 | C8: Build the as-is scoped to what the work in flight touches, plus one ring out | D8: Around thirty applications with owners and interfaces | G8: Publish it as "the architecture"
A9: First target | B9: 46-60 | C9: Write a target for one area, at a horizon matching a real decision | D9: A one-page target direction, agreed with the area owner | G9: Write an estate-wide target before you know the constraints
A10: First discipline | B10: 61-90 | C10: Seed the decision log with what was already decided. Add one thing to an existing process | D10: Eight to ten records, and one field on the intake form | G10: Stand up an architecture board. An empty agenda makes you decorative
A12: Phases complete: | D12: =COUNTIF(E5:E10,"Yes")&" of 6"
A14: Signals it converted
A15: Signal | C15: Seen? | D15: Date | E15: Note
A16: Somebody invites you before the decision rather than after | E16: The one that counts. Usually month three to five
A17: A decision gets cited by number, without you prompting | E17: The log became a shared memory rather than your filing
A18: A second project manager adds you to their board, unprompted | E18: The invitation spread on its own
A19: The integration team forwards you a request rather than refusing it | E19: You became a route rather than a reviewer
A20: Your as-is appears in somebody's slide without attribution | E20: The highest compliment this work receives
A21: Negative: every conversation you are in was initiated by you | E21: Three months in, this means you have been reviewing rather than helping
